{
  "CPU_List": [
    "i7-11",
    "i9-11",
    "i5-12",
    "i7-12",
    "i9-12",
    "i5-13",
    "i7-13",
    "i9-13",
    "i5-14",
    "i7-14",
    "i9-14",
    "Ultra 5 24",
    "Ultra 7 25",
    "Ultra 7 26",
    "Ultra 9 27",
    "Ultra 9 28",
    "Ryzen 5 5",
    "Ryzen 7 5",
    "Ryzen 7 PRO 5",
    "Ryzen 9 5",
    "Ryzen 5 7",
    "Ryzen 7 7",
    "Ryzen 7 PRO 7",
    "Ryzen 9 7",
    "Ryzen 9 PRO 7",
    "Ryzen 7 8",
    "Ryzen 7 PRO 8",
    "Ryzen 9 8",
    "Ryzen 5 9",
    "Ryzen 5 PRO 9",
    "Ryzen 7 9",
    "Ryzen 7 PRO 9",
    "Ryzen 9 9",
    "Ryzen 9 PRO 9",
    "Threadripper 7",
    "Threadripper 9",
    "Threadripper PRO 3",
    "Threadripper PRO 5",
    "Threadripper PRO 7",
    "Threadripper PRO 9"
  ],
  "GPU_List": [
    "RTX 3070",
    "RTX 3080",
    "RTX 3090",
    "RTX 40",
    "RTX 45",
    "RTX 50",
    "RTX 58",
    "RTX 60",
    "RTX A4",
    "RTX A5",
    "RTX A6",
    "RTX PRO 4",
    "RTX PRO 5",
    "RTX PRO 6",
    "RX 67",
    "RX 68",
    "RX 69",
    "RX 77",
    "RX 78",
    "RX 79",
    "RX 90",
    "Radeon Pro W6",
    "Radeon Pro W7",
    "Radeon AI PRO R9"
  ],
  "MEM_GB": 32,
  "VRAM_GB": 10,
  "VirtualMemory_GB": 10
}
